{
    "key": "group_5b0292ccbcc83",
    "title": "Theme option",
    "fields": [
        {
            "key": "field_5b029333f2cd3",
            "label": "Header",
            "name": "",
            "type": "tab",
            "instructions": "",
            "required": 0,
            "conditional_logic": 0,
            "wrapper": {
                "width": "",
                "class": "",
                "id": ""
            },
            "placement": "top",
            "endpoint": 0
        },
        {
            "key": "field_5b0292d667594",
            "label": "Logo",
            "name": "logo",
            "type": "image",
            "instructions": "",
            "required": 0,
            "conditional_logic": 0,
            "wrapper": {
                "width": "",
                "class": "",
                "id": ""
            },
            "return_format": "array",
            "preview_size": "thumbnail",
            "library": "all",
            "min_width": "",
            "min_height": "",
            "min_size": "",
            "max_width": "",
            "max_height": "",
            "max_size": "",
            "mime_types": ""
        },
        {
            "key": "field_5b02a13e51396",
            "label": "Button text header",
            "name": "button_text_header",
            "type": "text",
            "instructions": "",
            "required": 0,
            "conditional_logic": 0,
            "wrapper": {
                "width": "",
                "class": "",
                "id": ""
            },
            "default_value": "",
            "placeholder": "",
            "prepend": "",
            "append": "",
            "maxlength": ""
        },
        {
            "key": "field_5b02938fee712",
            "label": "Button link header",
            "name": "button_link_header",
            "type": "page_link",
            "instructions": "",
            "required": 0,
            "conditional_logic": 0,
            "wrapper": {
                "width": "",
                "class": "",
                "id": ""
            },
            "post_type": [],
            "taxonomy": [],
            "allow_null": 0,
            "allow_archives": 1,
            "multiple": 0
        },
        {
            "key": "field_5da5a36075f75",
            "label": "Social link",
            "name": "social_link",
            "type": "relationship",
            "instructions": "",
            "required": 0,
            "conditional_logic": 0,
            "wrapper": {
                "width": "",
                "class": "",
                "id": ""
            },
            "post_type": [
                "social-network"
            ],
            "taxonomy": "",
            "filters": [
                "search"
            ],
            "elements": "",
            "min": 0,
            "max": 5,
            "return_format": "object"
        },
        {
            "key": "field_5b029363f2cd4",
            "label": "Footer",
            "name": "",
            "type": "tab",
            "instructions": "",
            "required": 0,
            "conditional_logic": 0,
            "wrapper": {
                "width": "",
                "class": "",
                "id": ""
            },
            "placement": "top",
            "endpoint": 0
        },
        {
            "key": "field_5b02995c18c6b",
            "label": "Logo Footer",
            "name": "logo_footer",
            "type": "image",
            "instructions": "",
            "required": 0,
            "conditional_logic": 0,
            "wrapper": {
                "width": "",
                "class": "",
                "id": ""
            },
            "return_format": "array",
            "preview_size": "thumbnail",
            "library": "all",
            "min_width": "",
            "min_height": "",
            "min_size": "",
            "max_width": "",
            "max_height": "",
            "max_size": "",
            "mime_types": ""
        },
        {
            "key": "field_5b04c8ea6ba65",
            "label": "Tiêu đề form footer",
            "name": "title_form_footer",
            "type": "text",
            "instructions": "",
            "required": 0,
            "conditional_logic": 0,
            "wrapper": {
                "width": "",
                "class": "",
                "id": ""
            },
            "default_value": "",
            "placeholder": "",
            "prepend": "",
            "append": "",
            "maxlength": ""
        },
        {
            "key": "field_5db83d07d38e3",
            "label": "Nav Service",
            "name": "nav_service",
            "type": "group",
            "instructions": "",
            "required": 0,
            "conditional_logic": 0,
            "wrapper": {
                "width": "",
                "class": "",
                "id": ""
            },
            "layout": "block",
            "sub_fields": [
                {
                    "key": "field_5db83e8a668ce",
                    "label": "Title",
                    "name": "title",
                    "type": "text",
                    "instructions": "",
                    "required": 0,
                    "conditional_logic": 0,
                    "wrapper": {
                        "width": "",
                        "class": "",
                        "id": ""
                    },
                    "default_value": "",
                    "placeholder": "",
                    "prepend": "",
                    "append": "",
                    "maxlength": ""
                },
                {
                    "key": "field_5db83d30d38e4",
                    "label": "Select",
                    "name": "select",
                    "type": "select",
                    "instructions": "",
                    "required": 0,
                    "conditional_logic": 0,
                    "wrapper": {
                        "width": "",
                        "class": "",
                        "id": ""
                    },
                    "choices": [
                        "Default",
                        "Customer"
                    ],
                    "default_value": [],
                    "allow_null": 0,
                    "multiple": 0,
                    "ui": 0,
                    "return_format": "value",
                    "ajax": 0,
                    "placeholder": ""
                },
                {
                    "key": "field_5db83d71d38e5",
                    "label": "Service list",
                    "name": "service_list",
                    "type": "relationship",
                    "instructions": "",
                    "required": 0,
                    "conditional_logic": [
                        [
                            {
                                "field": "field_5db83d30d38e4",
                                "operator": "==",
                                "value": "1"
                            }
                        ]
                    ],
                    "wrapper": {
                        "width": "",
                        "class": "",
                        "id": ""
                    },
                    "post_type": [
                        "dich-vu"
                    ],
                    "taxonomy": "",
                    "filters": [
                        "search"
                    ],
                    "elements": [
                        "featured_image"
                    ],
                    "min": 1,
                    "max": 5,
                    "return_format": "object"
                }
            ]
        },
        {
            "key": "field_5b029ad318c6f",
            "label": "Footer form",
            "name": "footer _form",
            "type": "text",
            "instructions": "",
            "required": 0,
            "conditional_logic": 0,
            "wrapper": {
                "width": "",
                "class": "",
                "id": ""
            },
            "default_value": "",
            "placeholder": "",
            "prepend": "",
            "append": "",
            "maxlength": ""
        },
        {
            "key": "field_5ceb5ba983e47",
            "label": "Footer form English",
            "name": "footer _form_en",
            "type": "text",
            "instructions": "",
            "required": 0,
            "conditional_logic": 0,
            "wrapper": {
                "width": "",
                "class": "",
                "id": ""
            },
            "default_value": "",
            "placeholder": "",
            "prepend": "",
            "append": "",
            "maxlength": ""
        },
        {
            "key": "field_5dabe45a64e91",
            "label": "Company Name",
            "name": "company_name",
            "type": "text",
            "instructions": "",
            "required": 0,
            "conditional_logic": 0,
            "wrapper": {
                "width": "",
                "class": "",
                "id": ""
            },
            "default_value": "",
            "placeholder": "",
            "prepend": "",
            "append": "",
            "maxlength": ""
        },
        {
            "key": "field_5b02a669ea923",
            "label": "Banner Before Footer",
            "name": "",
            "type": "tab",
            "instructions": "",
            "required": 0,
            "conditional_logic": 0,
            "wrapper": {
                "width": "",
                "class": "",
                "id": ""
            },
            "placement": "top",
            "endpoint": 0
        },
        {
            "key": "field_5b02a67bea924",
            "label": "Background",
            "name": "background_before_footer",
            "type": "image",
            "instructions": "",
            "required": 0,
            "conditional_logic": 0,
            "wrapper": {
                "width": "",
                "class": "",
                "id": ""
            },
            "return_format": "array",
            "preview_size": "large",
            "library": "all",
            "min_width": "",
            "min_height": "",
            "min_size": "",
            "max_width": "",
            "max_height": "",
            "max_size": "",
            "mime_types": ""
        },
        {
            "key": "field_5b02a6a4ea925",
            "label": "Title",
            "name": "title_banner_before_footer",
            "type": "text",
            "instructions": "",
            "required": 0,
            "conditional_logic": 0,
            "wrapper": {
                "width": "",
                "class": "",
                "id": ""
            },
            "default_value": "",
            "placeholder": "",
            "prepend": "",
            "append": "",
            "maxlength": ""
        },
        {
            "key": "field_5b02a6bbea926",
            "label": "Button Text",
            "name": "button_text_before_footer",
            "type": "text",
            "instructions": "",
            "required": 0,
            "conditional_logic": 0,
            "wrapper": {
                "width": "",
                "class": "",
                "id": ""
            },
            "default_value": "",
            "placeholder": "",
            "prepend": "",
            "append": "",
            "maxlength": ""
        },
        {
            "key": "field_5b02a70dea927",
            "label": "Button link before footer",
            "name": "button_link_before_footer",
            "type": "page_link",
            "instructions": "",
            "required": 0,
            "conditional_logic": 0,
            "wrapper": {
                "width": "",
                "class": "",
                "id": ""
            },
            "post_type": [],
            "taxonomy": [],
            "allow_null": 0,
            "allow_archives": 1,
            "multiple": 0
        },
        {
            "key": "field_5b0377c632dee",
            "label": "Information",
            "name": "",
            "type": "tab",
            "instructions": "",
            "required": 0,
            "conditional_logic": 0,
            "wrapper": {
                "width": "",
                "class": "",
                "id": ""
            },
            "placement": "top",
            "endpoint": 0
        },
        {
            "key": "field_5b04c8d06ba64",
            "label": "Tiêu đề",
            "name": "title_information",
            "type": "text",
            "instructions": "",
            "required": 0,
            "conditional_logic": 0,
            "wrapper": {
                "width": "",
                "class": "",
                "id": ""
            },
            "default_value": "",
            "placeholder": "",
            "prepend": "",
            "append": "",
            "maxlength": ""
        },
        {
            "key": "field_5db12f65c3e34",
            "label": "Group HasTag",
            "name": "group_hastag",
            "type": "repeater",
            "instructions": "",
            "required": 0,
            "conditional_logic": 0,
            "wrapper": {
                "width": "",
                "class": "",
                "id": ""
            },
            "collapsed": "",
            "min": 0,
            "max": 3,
            "layout": "block",
            "button_label": "",
            "sub_fields": [
                {
                    "key": "field_5db12f7cc3e35",
                    "label": "Group cont",
                    "name": "group_cont",
                    "type": "repeater",
                    "instructions": "",
                    "required": 0,
                    "conditional_logic": 0,
                    "wrapper": {
                        "width": "",
                        "class": "",
                        "id": ""
                    },
                    "collapsed": "",
                    "min": 0,
                    "max": 5,
                    "layout": "table",
                    "button_label": "",
                    "sub_fields": [
                        {
                            "key": "field_5db12fbbc3e36",
                            "label": "name hastag",
                            "name": "name_hastag",
                            "type": "text",
                            "instructions": "",
                            "required": 0,
                            "conditional_logic": 0,
                            "wrapper": {
                                "width": "",
                                "class": "",
                                "id": ""
                            },
                            "default_value": "",
                            "placeholder": "",
                            "prepend": "",
                            "append": "",
                            "maxlength": ""
                        },
                        {
                            "key": "field_5db12fc6c3e37",
                            "label": "link hastag",
                            "name": "link_hastag",
                            "type": "url",
                            "instructions": "",
                            "required": 0,
                            "conditional_logic": 0,
                            "wrapper": {
                                "width": "",
                                "class": "",
                                "id": ""
                            },
                            "default_value": "",
                            "placeholder": ""
                        }
                    ]
                }
            ]
        },
        {
            "key": "field_5b0299e618c6c",
            "label": "Address",
            "name": "address",
            "type": "text",
            "instructions": "",
            "required": 0,
            "conditional_logic": 0,
            "wrapper": {
                "width": "",
                "class": "",
                "id": ""
            },
            "default_value": "",
            "placeholder": "",
            "prepend": "",
            "append": "",
            "maxlength": ""
        },
        {
            "key": "field_5b029a4b18c6e",
            "label": "Numberphone Mobile",
            "name": "numberphone_two",
            "type": "text",
            "instructions": "",
            "required": 0,
            "conditional_logic": 0,
            "wrapper": {
                "width": "",
                "class": "",
                "id": ""
            },
            "default_value": "",
            "placeholder": "",
            "prepend": "",
            "append": "",
            "maxlength": ""
        },
        {
            "key": "field_5b04e2c456936",
            "label": "Number Phone Mobile 2",
            "name": "number_phone_mobile_two",
            "type": "text",
            "instructions": "",
            "required": 0,
            "conditional_logic": 0,
            "wrapper": {
                "width": "",
                "class": "",
                "id": ""
            },
            "default_value": "",
            "placeholder": "",
            "prepend": "",
            "append": "",
            "maxlength": ""
        },
        {
            "key": "field_5b0292f467595",
            "label": "Number phone",
            "name": "number_phone",
            "type": "text",
            "instructions": "",
            "required": 0,
            "conditional_logic": 0,
            "wrapper": {
                "width": "",
                "class": "",
                "id": ""
            },
            "default_value": "",
            "placeholder": "",
            "prepend": "",
            "append": "",
            "maxlength": ""
        },
        {
            "key": "field_5b02931f67596",
            "label": "Email group",
            "name": "email_group",
            "type": "repeater",
            "instructions": "",
            "required": 0,
            "conditional_logic": 0,
            "wrapper": {
                "width": "",
                "class": "",
                "id": ""
            },
            "collapsed": "",
            "min": 1,
            "max": 3,
            "layout": "table",
            "button_label": "",
            "sub_fields": [
                {
                    "key": "field_5da6944fe6790",
                    "label": "Email",
                    "name": "email",
                    "type": "text",
                    "instructions": "",
                    "required": 0,
                    "conditional_logic": 0,
                    "wrapper": {
                        "width": "",
                        "class": "",
                        "id": ""
                    },
                    "default_value": "",
                    "placeholder": "",
                    "prepend": "",
                    "append": "",
                    "maxlength": ""
                }
            ]
        },
        {
            "key": "field_5ccaabe6ee890",
            "label": "Hotline",
            "name": "hotline",
            "type": "text",
            "instructions": "",
            "required": 0,
            "conditional_logic": 0,
            "wrapper": {
                "width": "",
                "class": "",
                "id": ""
            },
            "default_value": "",
            "placeholder": "",
            "prepend": "",
            "append": "",
            "maxlength": ""
        },
        {
            "key": "field_5b053b7520e6f",
            "label": "Page 404",
            "name": "",
            "type": "tab",
            "instructions": "",
            "required": 0,
            "conditional_logic": 0,
            "wrapper": {
                "width": "",
                "class": "",
                "id": ""
            },
            "placement": "top",
            "endpoint": 0
        },
        {
            "key": "field_5b069b2f42d5d",
            "label": "Background 404",
            "name": "bg_404",
            "type": "image",
            "instructions": "",
            "required": 0,
            "conditional_logic": 0,
            "wrapper": {
                "width": "",
                "class": "",
                "id": ""
            },
            "return_format": "array",
            "preview_size": "thumbnail",
            "library": "all",
            "min_width": "",
            "min_height": "",
            "min_size": "",
            "max_width": "",
            "max_height": "",
            "max_size": "",
            "mime_types": ""
        },
        {
            "key": "field_5b053b9320e70",
            "label": "Title 404",
            "name": "title_404",
            "type": "text",
            "instructions": "",
            "required": 0,
            "conditional_logic": 0,
            "wrapper": {
                "width": "",
                "class": "",
                "id": ""
            },
            "default_value": "",
            "placeholder": "",
            "prepend": "",
            "append": "",
            "maxlength": ""
        },
        {
            "key": "field_5b053ba920e71",
            "label": "Mô tả",
            "name": "description_404",
            "type": "text",
            "instructions": "",
            "required": 0,
            "conditional_logic": 0,
            "wrapper": {
                "width": "",
                "class": "",
                "id": ""
            },
            "default_value": "",
            "placeholder": "",
            "prepend": "",
            "append": "",
            "maxlength": ""
        },
        {
            "key": "field_5b053bc620e72",
            "label": "Button text home",
            "name": "button_text_home",
            "type": "text",
            "instructions": "",
            "required": 0,
            "conditional_logic": 0,
            "wrapper": {
                "width": "",
                "class": "",
                "id": ""
            },
            "default_value": "",
            "placeholder": "",
            "prepend": "",
            "append": "",
            "maxlength": ""
        },
        {
            "key": "field_5b0e6b2cfc219",
            "label": "Image Default",
            "name": "",
            "type": "tab",
            "instructions": "",
            "required": 0,
            "conditional_logic": 0,
            "wrapper": {
                "width": "",
                "class": "",
                "id": ""
            },
            "placement": "top",
            "endpoint": 0
        },
        {
            "key": "field_5b0e6b4ffc21a",
            "label": "Thumbnail Default",
            "name": "thumbnail_default",
            "type": "image",
            "instructions": "",
            "required": 0,
            "conditional_logic": 0,
            "wrapper": {
                "width": "",
                "class": "",
                "id": ""
            },
            "return_format": "array",
            "preview_size": "thumbnail",
            "library": "all",
            "min_width": "",
            "min_height": "",
            "min_size": "",
            "max_width": "",
            "max_height": "",
            "max_size": "",
            "mime_types": ""
        }
    ],
    "location": [
        [
            {
                "param": "options_page",
                "operator": "==",
                "value": "acf-options-theme-options"
            }
        ]
    ],
    "menu_order": 0,
    "position": "normal",
    "style": "default",
    "label_placement": "top",
    "instruction_placement": "label",
    "hide_on_screen": "",
    "active": 1,
    "description": "",
    "modified": 1572355742
}